{
  "type": "Feature",
  "stac_version": "1.1.0",
  "stac_extensions": [
    "https://landsat.usgs.gov/stac/landsat-extension/v1.1.1/schema.json",
    "https://stac-extensions.github.io/view/v1.0.0/schema.json",
    "https://stac-extensions.github.io/projection/v2.0.0/schema.json",
    "https://stac-extensions.github.io/file/v2.1.0/schema.json",
    "https://stac-extensions.github.io/eo/v1.1.0/schema.json",
    "https://stac-extensions.github.io/storage/v1.0.0/schema.json"
  ],
  "id": "LC08_L2SR_001113_20201015_20201105_02_T2_SR",
  "geometry": {
    "type": "Polygon",
    "coordinates": [
      [
        [
          -97.05556771158066,
          -74.41186192464036
        ],
        [
          -102.35336588614706,
          -73.50297264393076
        ],
        [
          -106.11608902466543,
          -74.90936686050638
        ],
        [
          -100.52189797806328,
          -75.90267344505557
        ],
        [
          -97.05556771158066,
          -74.41186192464036
        ]
      ]
    ]
  },
  "bbox": [
    -106.11608902466543,
    -75.90267344505557,
    -97.05556771158066,
    -73.50297264393076
  ],
  "properties": {
    "created": "2022-07-06T18:00:53.562000+00:00",
    "updated": "2022-07-06T18:00:53.562000+00:00",
    "datetime": "2020-10-15T14:52:10.641183Z",
    "platform": "LANDSAT_8",
    "proj:shape": [
      8441,
      8381
    ],
    "instruments": [
      "OLI",
      "TIRS"
    ],
    "eo:cloud_cover": 17.66,
    "proj:transform": [
      30,
      0,
      -1763415,
      0,
      -30,
      -206085
    ],
    "view:off_nadir": 0,
    "landsat:wrs_row": "113",
    "landsat:scene_id": "LC80011132020289LGN00",
    "landsat:wrs_path": "001",
    "landsat:wrs_type": "2",
    "view:sun_azimuth": 57.82925341,
    "landsat:correction": "L2SR",
    "view:sun_elevation": 17.34369141,
    "landsat:cloud_cover_land": 23.15,
    "landsat:collection_number": "02",
    "landsat:collection_category": "T2",
    "proj:code": "EPSG:3031"
  },
  "links": [
    {
      "rel": "root",
      "href": "../../../../../catalog.json",
      "type": "application/json",
      "title": "Earth Observing Dashboard"
    },
    {
      "rel": "collection",
      "href": "../../collection.json",
      "type": "application/json",
      "title": "Pine Island"
    },
    {
      "rel": "xyz",
      "href": "https://openveda.cloud/api/raster/collections/landsat-c2l2-sr-antarctic-glaciers-pine-island/items/LC08_L2SR_001113_20201015_20201105_02_T2_SR/tiles/WebMercatorQuad/{z}/{x}/{y}?&assets=red&assets=green&assets=blue&color_formula=gamma+RGB+2.7%2C+saturation+1.5%2C+sigmoidal+RGB+15+0.55&no_data=0",
      "type": "image/png",
      "title": "ADD_L2_Pine_Island"
    },
    {
      "rel": "parent",
      "href": "../../collection.json",
      "type": "application/json",
      "title": "Pine Island"
    }
  ],
  "assets": {
    "red": {
      "href": "s3://usgs-landsat/collection02/level-2/standard/oli-tirs/2020/001/113/LC08_L2SR_001113_20201015_20201105_02_T2/LC08_L2SR_001113_20201015_20201105_02_T2_SR_B4.TIF",
      "type": "image/vnd.stac.geotiff; cloud-optimized=true",
      "title": "Red Band (B4)",
      "description": "Collection 2 Level-2 Red Band (B4) Surface Reflectance",
      "eo:bands": [
        {
          "gsd": 30,
          "name": "B4",
          "common_name": "red",
          "center_wavelength": 0.65
        }
      ],
      "file:checksum": "134050b8416781e829eb04f64947115fa23ab85c33e5fc01a6b0f4120251ae58ab97e293a983911607fb1baa655ae1872c931d7588f3a0e8600829676d23340289df",
      "roles": [
        "data"
      ]
    },
    "blue": {
      "href": "s3://usgs-landsat/collection02/level-2/standard/oli-tirs/2020/001/113/LC08_L2SR_001113_20201015_20201105_02_T2/LC08_L2SR_001113_20201015_20201105_02_T2_SR_B2.TIF",
      "type": "image/vnd.stac.geotiff; cloud-optimized=true",
      "title": "Blue Band (B2)",
      "description": "Collection 2 Level-2 Blue Band (B2) Surface Reflectance",
      "eo:bands": [
        {
          "gsd": 30,
          "name": "B2",
          "common_name": "blue",
          "center_wavelength": 0.48
        }
      ],
      "file:checksum": "13406e2ecf19b6fad4dd5b13afaf5ebf46cd2fcb45dc2440c71533f34f0ce9e41f4f0f06a552bbd1804d30bc048d1606f328f7b77cd9c852785aa6bdade14f0e9aec",
      "roles": [
        "data"
      ]
    },
    "green": {
      "href": "s3://usgs-landsat/collection02/level-2/standard/oli-tirs/2020/001/113/LC08_L2SR_001113_20201015_20201105_02_T2/LC08_L2SR_001113_20201015_20201105_02_T2_SR_B3.TIF",
      "type": "image/vnd.stac.geotiff; cloud-optimized=true",
      "title": "Green Band (B3)",
      "description": "Collection 2 Level-2 Green Band (B3) Surface Reflectance",
      "eo:bands": [
        {
          "gsd": 30,
          "name": "B3",
          "common_name": "green",
          "center_wavelength": 0.56
        }
      ],
      "file:checksum": "1340039396de502e82565ba08ea73593db0424d51668b618adf8248f4a26e49c4e1fb3db672cfdeffb574ca3f5ba05295dda85a403bae03e5ceaa04a08021de98734",
      "roles": [
        "data"
      ]
    },
    "index": {
      "href": "https://landsatlook.usgs.gov/stac-browser/collection02/level-2/standard/oli-tirs/2020/001/113/LC08_L2SR_001113_20201015_20201105_02_T2/LC08_L2SR_001113_20201015_20201105_02_T2"
    },
    "nir08": {
      "href": "s3://usgs-landsat/collection02/level-2/standard/oli-tirs/2020/001/113/LC08_L2SR_001113_20201015_20201105_02_T2/LC08_L2SR_001113_20201015_20201105_02_T2_SR_B5.TIF",
      "file:checksum": "13405340d38a0a8486fd7f357aa31806935af5e5ea4644931f05054f97c26c75181c5c098e6117c04da6c46d947f1120100d1944940a243843c67861f9ee86849a38"
    },
    "swir16": {
      "href": "s3://usgs-landsat/collection02/level-2/standard/oli-tirs/2020/001/113/LC08_L2SR_001113_20201015_20201105_02_T2/LC08_L2SR_001113_20201015_20201105_02_T2_SR_B6.TIF",
      "file:checksum": "1340189f546161ed2d1aa1a43b9a24e6e61661560962cef04c5dcfd5a9a206b0c1848322546d5131f252b233db86b683d56ef5f8b9080f5820c34ddd69da7c6ad42a"
    },
    "swir22": {
      "href": "s3://usgs-landsat/collection02/level-2/standard/oli-tirs/2020/001/113/LC08_L2SR_001113_20201015_20201105_02_T2/LC08_L2SR_001113_20201015_20201105_02_T2_SR_B7.TIF",
      "file:checksum": "13405d3b7d048fbf697860bf7be032a9f7a8a828731ae7eedd052e063bebf0751c35eb43863652e848be04b4b9a4a7e576846462f680a01796cf717c2598a2a61a3d"
    },
    "ANG.txt": {
      "href": "s3://usgs-landsat/collection02/level-2/standard/oli-tirs/2020/001/113/LC08_L2SR_001113_20201015_20201105_02_T2/LC08_L2SR_001113_20201015_20201105_02_T2_ANG.txt",
      "file:checksum": "13403bd4b9c3f10052a4c72b9224ee270fba0bdd3b4fa132624d9c6c8c5ae0ec312d5d5b447b336d3ee1087846879f774b4a7a88e3a7ab6fbde16be6f592d6906d68"
    },
    "MTL.txt": {
      "href": "s3://usgs-landsat/collection02/level-2/standard/oli-tirs/2020/001/113/LC08_L2SR_001113_20201015_20201105_02_T2/LC08_L2SR_001113_20201015_20201105_02_T2_MTL.txt",
      "file:checksum": "1340035f9152ba7374b243db1c30574ae700aa0b1d23c56f2810ee157fbd3d016746b8611990869b6ca0f9d8b13fdd1c66730fb32378314416c0d510328279db5d69"
    },
    "MTL.xml": {
      "href": "s3://usgs-landsat/collection02/level-2/standard/oli-tirs/2020/001/113/LC08_L2SR_001113_20201015_20201105_02_T2/LC08_L2SR_001113_20201015_20201105_02_T2_MTL.xml",
      "description": "Collection 2 Level-1 Product Metadata File (xml)",
      "file:checksum": "13403c679c1e0acd431237a1855e911999d33c0da8e19fa4062fee994aa739a318aecae512dbb37d0ad092ae6eef0a5d6b831220ba38e1dd505430866915f6220c45"
    },
    "coastal": {
      "href": "s3://usgs-landsat/collection02/level-2/standard/oli-tirs/2020/001/113/LC08_L2SR_001113_20201015_20201105_02_T2/LC08_L2SR_001113_20201015_20201105_02_T2_SR_B1.TIF",
      "file:checksum": "1340e7eb7af35e0566032cc9ed464466ab30aba6ccc5d5c7d629ac79a83ccb4992e71fe4d88a332688b155fe8f280d83c0591176951ed7e5fd6f15af3417c0ac537f"
    },
    "MTL.json": {
      "href": "s3://usgs-landsat/collection02/level-2/standard/oli-tirs/2020/001/113/LC08_L2SR_001113_20201015_20201105_02_T2/LC08_L2SR_001113_20201015_20201105_02_T2_MTL.json",
      "file:checksum": "1340e75db924f2fbec888fa403aa450243a08cb6f45564aeaa6ed81d90eb61d574963a866e7ef893e6f6df60581e9132b2db35e11429aab2acc14845505c7708b22a"
    },
    "qa_pixel": {
      "href": "s3://usgs-landsat/collection02/level-2/standard/oli-tirs/2020/001/113/LC08_L2SR_001113_20201015_20201105_02_T2/LC08_L2SR_001113_20201015_20201105_02_T2_QA_PIXEL.TIF",
      "file:checksum": "134071884bda34f2889a4ee94e6b316e71b535f84f1ed4be05509d33ff31d195aad917f4df51b9dcbf2a91883353b2451e00f1661098b19e9c56ee520f98ec828596"
    },
    "qa_radsat": {
      "href": "s3://usgs-landsat/collection02/level-2/standard/oli-tirs/2020/001/113/LC08_L2SR_001113_20201015_20201105_02_T2/LC08_L2SR_001113_20201015_20201105_02_T2_QA_RADSAT.TIF",
      "file:checksum": "1340cce7c821f85724736ca6b1206becb0beeea74c879cac85152430f75487ff01f37a5033df35fd3aa7a9b7c6d886348d90f3dde7b73ec73fbb97bfcde1b63117d6"
    },
    "thumbnail": {
      "href": "s3://usgs-landsat/collection02/level-2/standard/oli-tirs/2020/001/113/LC08_L2SR_001113_20201015_20201105_02_T2/LC08_L2SR_001113_20201015_20201105_02_T2_thumb_small.jpeg",
      "type": "image/jpeg",
      "title": "Thumbnail image",
      "file:checksum": "1340c07ef1761ffb18913f929aefe81e85f686cbdbc3d194cd2544ea8b606590af50beacdc042d1a4c1177a976e9b1a8285674a71bc1aa1b3f48464fa44d620b1f87",
      "roles": [
        "thumbnail"
      ]
    },
    "qa_aerosol": {
      "href": "s3://usgs-landsat/collection02/level-2/standard/oli-tirs/2020/001/113/LC08_L2SR_001113_20201015_20201105_02_T2/LC08_L2SR_001113_20201015_20201105_02_T2_SR_QA_AEROSOL.TIF",
      "description": "Collection 2 Level-2 Aerosol Quality Analysis Band (ANG) Surface Reflectance",
      "file:checksum": "1340b0ac0891bc0223eea1af0dd5f915f569f44a43015ad1688db35ba7dd40d73812ece67531a23cbb49f89c31dfafedf502baff3739392aefefbc462ca52d126ab7"
    },
    "reduced_resolution_browse": {
      "href": "s3://usgs-landsat/collection02/level-2/standard/oli-tirs/2020/001/113/LC08_L2SR_001113_20201015_20201105_02_T2/LC08_L2SR_001113_20201015_20201105_02_T2_thumb_large.jpeg",
      "file:checksum": "13402b7bf850a3dbc386109bde7555ce6b76818d94f0d55de8bf192f53b211ec8059595da11da7a95ba0bdd39f147f1e5e525453dd329ed39af08e39eacc04c56ad2"
    }
  },
  "collection": "landsat-c2l2-sr-antarctic-glaciers-pine-island"
}